<annotation>
<folder>train</folder>
<filename>bf491fe4-P7070117.JPG</filename>
<source>
<database>MyDatabase</database>
<annotation>COCO2017</annotation>
<image>flickr</image>
<flickrid>NULL</flickrid>
<annotator>1</annotator>
</source>
<owner>
<flickrid>NULL</flickrid>
<name>Label Studio</name>
</owner>
<size>
<width>4000</width>
<height>3000</height>
<depth>3</depth>
</size>
<segmented>0</segmented>
<object>
<name>Counted_Objects</name>
<pose>Unspecified</pose>
<truncated>0</truncated>
<difficult>0</difficult>
<bndbox>
<xmin>2214</xmin>
<ymin>657</ymin>
<xmax>2699</xmax>
<ymax>2176</ymax>
</bndbox>
</object>
<object>
<name>Counted_Objects</name>
<pose>Unspecified</pose>
<truncated>0</truncated>
<difficult>0</difficult>
<bndbox>
<xmin>2840</xmin>
<ymin>714</ymin>
<xmax>3286</xmax>
<ymax>2194</ymax>
</bndbox>
</object>
<object>
<name>Not_Counted_Objects</name>
<pose>Unspecified</pose>
<truncated>0</truncated>
<difficult>0</difficult>
<bndbox>
<xmin>1717</xmin>
<ymin>504</ymin>
<xmax>2068</xmax>
<ymax>2406</ymax>
</bndbox>
</object>
<object>
<name>Not_Counted_Objects</name>
<pose>Unspecified</pose>
<truncated>0</truncated>
<difficult>0</difficult>
<bndbox>
<xmin>587</xmin>
<ymin>868</ymin>
<xmax>1576</xmax>
<ymax>1876</ymax>
</bndbox>
</object>
</annotation>